outerbounds_app_client/__init__.py
outerbounds_app_client/app_client.py
outerbounds_app_client-0.0.6.dist-info/METADATA
outerbounds_app_client-0.0.6.dist-info/WHEEL
outerbounds_app_client-0.0.6.dist-info/top_level.txt
outerbounds_app_client-0.0.6.dist-info/RECORD
