Metadata-Version: 2.1
Name: outerbounds-app-client
Version: 0.0.6
Summary: Experimental client for interacting with Outerbounds apps programmatically
Author: Outerbounds, Inc.
License: Commercial
Requires-Dist: boto3
Requires-Dist: requests
